arcane/__init__.py
arcane/api/__init__.py
arcane/api/authentication_api.py
arcane/api/pr_retrieval_api.py
arcane/api/repository_installation_api.py
arcane/api/task_creation_api.py
arcane/api/task_retrieval_api.py
arcane/api_client.py
arcane/api_response.py
arcane/configuration.py
arcane/docs/AuthenticationApi.md
arcane/docs/BadRequest.md
arcane/docs/Input.md
arcane/docs/InstallationStatus.md
arcane/docs/NotFound.md
arcane/docs/Output.md
arcane/docs/PRNumberResponse.md
arcane/docs/PRRetrievalApi.md
arcane/docs/Prompt.md
arcane/docs/RepoBranchInput.md
arcane/docs/RepositoryInstallationApi.md
arcane/docs/Task.md
arcane/docs/TaskCreationApi.md
arcane/docs/TaskRetrievalApi.md
arcane/engine.py
arcane/exceptions.py
arcane/models/__init__.py
arcane/models/bad_request.py
arcane/models/input.py
arcane/models/installation_status.py
arcane/models/not_found.py
arcane/models/output.py
arcane/models/pr_number_response.py
arcane/models/prompt.py
arcane/models/repo_branch_input.py
arcane/models/task.py
arcane/rest.py
arcane/test/__init__.py
arcane/test/test_authentication_api.py
arcane/test/test_bad_request.py
arcane/test/test_input.py
arcane/test/test_installation_status.py
arcane/test/test_not_found.py
arcane/test/test_output.py
arcane/test/test_pr_number_response.py
arcane/test/test_pr_retrieval_api.py
arcane/test/test_prompt.py
arcane/test/test_repo_branch_input.py
arcane/test/test_repository_installation_api.py
arcane/test/test_task.py
arcane/test/test_task_creation_api.py
arcane/test/test_task_retrieval_api.py
arcane/util.py
arcane_engine-1.12.1.dist-info/LICENSE
arcane_engine-1.12.1.dist-info/METADATA
arcane_engine-1.12.1.dist-info/WHEEL
arcane_engine-1.12.1.dist-info/RECORD
