Metadata-Version: 2.1
Name: arcane-engine
Version: 1.12.1
Summary: Python SDK for Arcane Engine, a text-to-task automation platform.
Home-page: https://github.com/arc-eng/kit
License: GPL-3.0
Author: Marco Lamina
Author-email: marco@arcane.engineer
Requires-Python: >=3.10
Classifier: License :: OSI Approved :: GNU General Public License v3 (GPLv3)
Classifier: Programming Language :: Python :: 3
Classifier: Programming Language :: Python :: 3.10
Classifier: Programming Language :: Python :: 3.11
Classifier: Programming Language :: Python :: 3.12
Classifier: Programming Language :: Python :: 3.13
Requires-Dist: pydantic (<2.7)
Requires-Dist: python-dateutil (==2.9.0)
Requires-Dist: urllib3 (==2.2.1)
Requires-Dist: wheel (==0.42.0)
Project-URL: Repository, https://github.com/arc-eng/kit
